build/lib/build/lib/src/pygraspi_test/__init__.py
build/lib/build/lib/src/pygraspi_test/helloWorld/__init__.py
build/lib/build/lib/src/pygraspi_test/helloWorld/helloWorld.py
build/lib/build/lib/src/pygraspi_test/operations/__init__.py
build/lib/build/lib/src/pygraspi_test/operations/add.py
build/lib/src/pygraspi_test/__init__.py
build/lib/src/pygraspi_test/helloWorld/__init__.py
build/lib/src/pygraspi_test/helloWorld/helloWorld.py
build/lib/src/pygraspi_test/operations/__init__.py
build/lib/src/pygraspi_test/operations/add.py
pygraspi_test-0.2.1.dist-info/licenses/LICENSE
src/pygraspi_test/__init__.py
src/pygraspi_test/helloWorld/__init__.py
src/pygraspi_test/helloWorld/helloWorld.py
src/pygraspi_test/operations/__init__.py
src/pygraspi_test/operations/add.py
pygraspi_test-0.2.1.dist-info/METADATA
pygraspi_test-0.2.1.dist-info/WHEEL
pygraspi_test-0.2.1.dist-info/top_level.txt
pygraspi_test-0.2.1.dist-info/RECORD
